toolsandogh/__init__.py
toolsandogh/_canonicalize_video.py
toolsandogh/_generate_video.py
toolsandogh/_load_video.py
toolsandogh/_plot_video.py
toolsandogh/_render.py
toolsandogh/_rolling.py
toolsandogh/_rvt.py
toolsandogh/_store_video.py
toolsandogh/_validate_video.py
toolsandogh/scripts/__init__.py
toolsandogh/scripts/convert.py
toolsandogh/scripts/iscat_analysis.py
toolsandogh/tests/__init__.py
toolsandogh/tests/conftest.py
toolsandogh/tests/test_io.py
toolsandogh/tests/test_iscat_analysis.py
toolsandogh/tests/test_rolling.py
toolsandogh/tests/testfile.tiff
toolsandogh/utils/__init__.py
toolsandogh/utils/mproctest.py
toolsandogh-0.1.2.dist-info/licenses/LICENSE
toolsandogh-0.1.2.dist-info/METADATA
toolsandogh-0.1.2.dist-info/WHEEL
toolsandogh-0.1.2.dist-info/top_level.txt
toolsandogh-0.1.2.dist-info/RECORD
