Metadata-Version: 2.4
Name: toolsandogh
Version: 0.1.2
Summary: A collection of Python scripts for iSCAT microscopy data analysis
Author-email: Marco Heisig <marco.heisig@mpl.mpg.de>
License-Expression: GPL-3.0-or-later
Project-URL: Repository, https://github.com/SandoghdarLab/toolsandogh
Project-URL: Issues, https://github.com/SandoghdarLab/toolsandogh/issues
Keywords: tools,utilities,python,microscopy
Requires-Python: <3.13,>=3.12
License-File: LICENSE
Requires-Dist: imgui[glfw,sdl2]
Requires-Dist: fastplotlib[imgui]
Requires-Dist: fsspec[fuse]
Requires-Dist: imageio[ffmpeg]
Requires-Dist: numpy
Requires-Dist: pyarrow
Requires-Dist: scipy
Requires-Dist: scikit-image
Requires-Dist: trackpy
Requires-Dist: imgrvt
Requires-Dist: tqdm
Requires-Dist: bioio
Requires-Dist: bioio-bioformats
Requires-Dist: bioio-czi
Requires-Dist: scipy
Requires-Dist: scikit-image
Requires-Dist: trackpy
Requires-Dist: imgrvt
Requires-Dist: tqdm
Requires-Dist: imageio[ffmpeg]
Requires-Dist: bioio
Requires-Dist: bioio-bioformats
Requires-Dist: bioio-czi
Requires-Dist: bioio-dv
Requires-Dist: bioio-imageio
Requires-Dist: bioio-lif
Requires-Dist: bioio-nd2
Requires-Dist: bioio-ome-tiff>=1.4
Requires-Dist: bioio-ome-zarr>=2.2
Requires-Dist: bioio-sldy
Requires-Dist: bioio-tifffile
Requires-Dist: bioio-tiff-glob
Requires-Dist: bioio-imageio>=1.2
Requires-Dist: ome-types
Requires-Dist: xarray
Requires-Dist: dask
Dynamic: license-file
